conversant/__init__.py
conversant/chatbot.py
conversant/demo/__init__.py
conversant/demo/streamlit_example.py
conversant/demo/styles.css
conversant/demo/ui.py
conversant/demo/utils.py
conversant/personas/client-support/config.json
conversant/personas/fantasy-wizard/config.json
conversant/personas/fortune-teller/config.json
conversant/personas/historian/config.json
conversant/personas/injured-person/config.json
conversant/personas/math-teacher/config.json
conversant/personas/personal-trainer/config.json
conversant/personas/travel-advisor/config.json
conversant/personas/watch-sales-agent/config.json
conversant/prompt_chatbot.py
conversant/prompts/__init__.py
conversant/prompts/chat_prompt.py
conversant/prompts/prompt.py
conversant/prompts/rewrite_prompt.py
conversant/search/__init__.py
conversant/search/document.py
conversant/search/local_searcher.py
conversant/search/searcher.py
conversant/utils/__init__.py
conversant/utils/demo_utils.py
conversant-0.2.5.dist-info/LICENSE
conversant-0.2.5.dist-info/WHEEL
conversant-0.2.5.dist-info/METADATA
conversant-0.2.5.dist-info/RECORD
