Metadata-Version: 2.1
Name: conversant
Version: 0.2.5
Summary: Conversational AI tooling
Home-page: https://github.com/cohere-ai/sandbox-conversant-lib
Author: Cohere ConvAI
Author-email: convai@cohere.com
Requires-Python: >=3.8, !=2.7.*, !=3.0.*, !=3.1.*, !=3.2.*, !=3.3.*, !=3.4.*, !=3.5.*, !=3.6.*, !=3.7.*
Classifier: Programming Language :: Python :: 3
Classifier: Programming Language :: Python :: 3.8
Classifier: Programming Language :: Python :: 3.9
Classifier: Programming Language :: Python :: 3.10
Requires-Dist: cohere (>=3.0,<4.0)
Requires-Dist: emoji (==1.7.0)
Requires-Dist: emojificate (>=0.6.0,<0.7.0)
Requires-Dist: pydantic (>=1.10.2,<2.0.0)
Requires-Dist: streamlit-ace (>=0.1.1,<0.2.0)
Requires-Dist: streamlit-talk (>=0.2.1,<0.3.0)
Requires-Dist: toml (>=0.10.2,<0.11.0)
Project-URL: Repository, https://github.com/cohere-ai/sandbox-conversant-lib
